odoo9_addon_product_multi_image-9.0.1.0.0-py2.7-nspkg.pth
odoo9_addon_product_multi_image-9.0.1.0.0.dist-info/top_level.txt
odoo9_addon_product_multi_image-9.0.1.0.0.dist-info/WHEEL
odoo9_addon_product_multi_image-9.0.1.0.0.dist-info/RECORD
odoo9_addon_product_multi_image-9.0.1.0.0.dist-info/metadata.json
odoo9_addon_product_multi_image-9.0.1.0.0.dist-info/DESCRIPTION.rst
odoo9_addon_product_multi_image-9.0.1.0.0.dist-info/METADATA
odoo9_addon_product_multi_image-9.0.1.0.0.dist-info/namespace_packages.txt
odoo_addons/product_multi_image/__openerp__.py
odoo_addons/product_multi_image/hooks.py
odoo_addons/product_multi_image/__init__.py
odoo_addons/product_multi_image/README.rst
odoo_addons/product_multi_image/models/product_template.py
odoo_addons/product_multi_image/models/product_product.py
odoo_addons/product_multi_image/models/__init__.py
odoo_addons/product_multi_image/models/image.py
odoo_addons/product_multi_image/i18n/es.po
odoo_addons/product_multi_image/i18n/sv.po
odoo_addons/product_multi_image/views/image_view.xml
odoo_addons/product_multi_image/views/product_template_view.xml
odoo_addons/product_multi_image/tests/test_product_multi_image.py
odoo_addons/product_multi_image/tests/__init__.py
odoo_addons/product_multi_image/images/file.png
odoo_addons/product_multi_image/images/url.png
odoo_addons/product_multi_image/images/db.png
odoo_addons/product_multi_image/images/product.png
odoo_addons/product_multi_image/static/description/icon.svg
odoo_addons/product_multi_image/static/description/icon.png
