Metadata-Version: 2.0
Name: odoo9-addon-product-multi-image
Version: 9.0.1.0.0
Summary: Multiple Images in Products
Home-page: https://www.tecnativa.com
Author: Antiun Ingeniería, Tecnativa, LasLabs, Odoo Community Association (OCA)
Author-email: support@odoo-community.org
License: AGPL-3
Platform: UNKNOWN
Requires-Dist: odoo (<9.1a,>=9.0a)
Requires-Dist: odoo9-addon-base-multi-image
Classifier: Programming Language :: Python :: 2.7
Classifier: Framework :: Odoo
Classifier: License :: OSI Approved :: GNU Affero General Public License v3
